arionxiv/__init__.py
arionxiv/__main__.py
arionxiv/github_actions_runner.py
arionxiv/main.py
arionxiv/scheduler_daemon.py
arionxiv/server.py
arionxiv/server_main.py
arionxiv/arxiv_operations/__init__.py
arionxiv/arxiv_operations/client.py
arionxiv/arxiv_operations/fetcher.py
arionxiv/arxiv_operations/searcher.py
arionxiv/arxiv_operations/utils.py
arionxiv/cli/__init__.py
arionxiv/cli/main.py
arionxiv/cli/commands/__init__.py
arionxiv/cli/commands/analyze.py
arionxiv/cli/commands/auth.py
arionxiv/cli/commands/chat.py
arionxiv/cli/commands/daily.py
arionxiv/cli/commands/fetch.py
arionxiv/cli/commands/library.py
arionxiv/cli/commands/preferences.py
arionxiv/cli/commands/search.py
arionxiv/cli/commands/settings_unified.py
arionxiv/cli/commands/trending.py
arionxiv/cli/commands/welcome.py
arionxiv/cli/ui/__init__.py
arionxiv/cli/ui/global_theme_manager.py
arionxiv/cli/ui/logo.py
arionxiv/cli/ui/splash.py
arionxiv/cli/ui/theme.py
arionxiv/cli/ui/theme_system.py
arionxiv/cli/utils/__init__.py
arionxiv/cli/utils/animations.py
arionxiv/cli/utils/api_client.py
arionxiv/cli/utils/api_config.py
arionxiv/cli/utils/command_suggestions.py
arionxiv/cli/utils/db_config_manager.py
arionxiv/prompts/__init__.py
arionxiv/prompts/prompts.py
arionxiv/rag_techniques/__init__.py
arionxiv/rag_techniques/basic_rag.py
arionxiv/services/__init__.py
arionxiv/services/llm_client.py
arionxiv/services/unified_analysis_service.py
arionxiv/services/unified_auth_service.py
arionxiv/services/unified_config_service.py
arionxiv/services/unified_daily_dose_service.py
arionxiv/services/unified_database_service.py
arionxiv/services/unified_llm_service.py
arionxiv/services/unified_paper_service.py
arionxiv/services/unified_pdf_service.py
arionxiv/services/unified_prompt_service.py
arionxiv/services/unified_scheduler_service.py
arionxiv/services/unified_user_service.py
arionxiv/services/llm_inference/__init__.py
arionxiv/services/llm_inference/groq_client.py
arionxiv/services/llm_inference/llm_utils.py
arionxiv-1.0.37.dist-info/licenses/LICENSE
arionxiv-1.0.37.dist-info/METADATA
arionxiv-1.0.37.dist-info/WHEEL
arionxiv-1.0.37.dist-info/entry_points.txt
arionxiv-1.0.37.dist-info/top_level.txt
arionxiv-1.0.37.dist-info/RECORD
