Metadata-Version: 2.4
Name: arionxiv
Version: 1.0.37
Summary: AI-Powered Research Paper Analysis and Management System
Home-page: https://github.com/ArionDas/ArionXiv
Author: Arion Das
Author-email: Arion Das <ariondasad@gmail.com>
Maintainer-email: Arion Das <ariondasad@gmail.com>
License: MIT
Project-URL: Homepage, https://github.com/ArionDas/ArionXiv
Project-URL: Documentation, https://github.com/ArionDas/ArionXiv#readme
Project-URL: Repository, https://github.com/ArionDas/ArionXiv
Project-URL: Bug Tracker, https://github.com/ArionDas/ArionXiv/issues
Keywords: arxiv,research,papers,ai,machine-learning,nlp,analysis,academic,scientific,publication,pdf,text-extraction,mongodb,cli,api
Platform: any
Classifier: Development Status :: 4 - Beta
Classifier: Intended Audience :: Developers
Classifier: Intended Audience :: Science/Research
Classifier: Intended Audience :: Education
Classifier: Topic :: Scientific/Engineering :: Artificial Intelligence
Classifier: Topic :: Text Processing :: Linguistic
Classifier: Topic :: Database :: Front-Ends
Classifier: License :: OSI Approved :: MIT License
Classifier: Programming Language :: Python :: 3
Classifier: Programming Language :: Python :: 3.8
Classifier: Programming Language :: Python :: 3.9
Classifier: Programming Language :: Python :: 3.10
Classifier: Programming Language :: Python :: 3.11
Classifier: Programming Language :: Python :: 3.12
Classifier: Operating System :: OS Independent
Classifier: Environment :: Console
Classifier: Environment :: Web Environment
Requires-Python: >=3.8
License-File: LICENSE
Requires-Dist: rich>=13.0.0
Requires-Dist: click>=8.0.0
Requires-Dist: colorama>=0.4.6
Requires-Dist: requests>=2.31.0
Requires-Dist: aiohttp>=3.8.0
Requires-Dist: httpx>=0.24.0
Requires-Dist: PyPDF2>=3.0.0
Requires-Dist: pymupdf>=1.23.0
Requires-Dist: Pillow>=9.0.0
Requires-Dist: pdfplumber>=0.10.0
Requires-Dist: pytesseract>=0.3.10
Requires-Dist: tabula-py>=2.9.0
Requires-Dist: opencv-python>=4.8.0
Requires-Dist: arxiv>=2.0.0
Requires-Dist: pydantic>=2.0.0
Requires-Dist: python-dotenv>=1.0.0
Requires-Dist: PyJWT>=2.8.0
Requires-Dist: structlog>=23.0.0
Requires-Dist: numpy<2.0.0,>=1.24.0
Requires-Dist: google-genai>=1.0.0
Requires-Dist: groq>=0.4.0
Requires-Dist: sentence-transformers>=3.0.0
Requires-Dist: torch>=2.0.0
Requires-Dist: transformers>=4.20.0
Requires-Dist: pymongo<5.0,>=4.9
Requires-Dist: motor>=3.0.0
Provides-Extra: dev
Requires-Dist: pytest>=7.0.0; extra == "dev"
Requires-Dist: pytest-asyncio>=0.21.0; extra == "dev"
Requires-Dist: black>=23.0.0; extra == "dev"
Requires-Dist: flake8>=6.0.0; extra == "dev"
Requires-Dist: mypy>=1.0.0; extra == "dev"
Requires-Dist: pre-commit>=3.0.0; extra == "dev"
Dynamic: author
Dynamic: home-page
Dynamic: license-file
Dynamic: platform
Dynamic: requires-python
